recurring/__init__.py
recurring-2.0.0.dist-info/LICENSE.txt
recurring-2.0.0.dist-info/METADATA
recurring-2.0.0.dist-info/RECORD
recurring-2.0.0.dist-info/WHEEL
recurring-2.0.0.dist-info/top_level.txt
