Metadata-Version: 2.1
Name: recurring
Version: 2.0.0
Summary: Run a function or other callable every N seconds
Home-page: https://github.com/jdodds/recurring
Author: Jeremiah Dodds
Author-email: jeremiah.dodds@gmail.com
License: UNKNOWN
Project-URL: Issue Tracker, https://github.com/jdodds/recurring/issues
Project-URL: Source, https://github.com/jdodds/recurring
Project-URL: Docs, https://recurring.readthedocs.io
Keywords: scheduling repeating cron sched threads
Platform: UNKNOWN
Classifier: Development Status :: 5 - Production/Stable
Classifier: Intended Audience :: Developers
Classifier: License :: OSI Approved :: MIT License
Classifier: Operating System :: OS Independent
Classifier: Natural Language :: English
Classifier: Topic :: Software Development :: Libraries :: Python Modules
Classifier: Programming Language :: Python :: 3.6
Classifier: Programming Language :: Python :: Implementation :: CPython
Requires-Python: >=3.6
Provides-Extra: docs
Provides-Extra: docs
Requires-Dist: m2r; extra == 'docs'
